gldb/__init__.py
gldb/_version.py
gldb/gldb.py
gldb/stores.py
gldb/query/__init__.py
gldb/query/data_store_query.py
gldb/query/metadata_query.py
gldb/query/query.py
gldb/query/utils.py
gldb-2.1.1.dist-info/licenses/LICENSE
tests/__init__.py
tests/example_storage_db.py
tests/test_generic_linked_database.py
tests/test_graphdb.py
tests/test_query.py
tests/test_stores.py
tests/test_version.py
tests/data/__init__.py
gldb-2.1.1.dist-info/METADATA
gldb-2.1.1.dist-info/WHEEL
gldb-2.1.1.dist-info/top_level.txt
gldb-2.1.1.dist-info/RECORD
