Metadata-Version: 2.4
Name: gldb
Version: 2.1.1
Summary: Generic linked database approach to manage RDF and raw data together.
Home-page: https://github.com/matthiasprobst/generic-linked-database
Author: Matthias Probst
Author-email: matth.probst@gmail.com
Classifier: Programming Language :: Python :: 3
Classifier: Programming Language :: Python :: 3.9
Classifier: Programming Language :: Python :: 3.10
Classifier: Programming Language :: Python :: 3.11
Classifier: Programming Language :: Python :: 3.12
Classifier: Programming Language :: Python :: 3.13
Classifier: License :: OSI Approved :: MIT License
Classifier: Operating System :: OS Independent
Classifier: Development Status :: 4 - Beta
Requires-Python: <3.14,>3.8
License-File: LICENSE
Requires-Dist: requests~=2.32
Requires-Dist: appdirs~=1.4
Requires-Dist: rdflib~=7.1
Provides-Extra: test
Requires-Dist: pytest<=9.0.0,>=8.3.2; extra == "test"
Requires-Dist: pytest-cov<=6.0.0,>=5.0.0; extra == "test"
Requires-Dist: pandas; extra == "test"
Provides-Extra: tutorial
Requires-Dist: pandas; extra == "tutorial"
Provides-Extra: complete
Requires-Dist: pytest<=9.0.0,>=8.3.2; extra == "complete"
Requires-Dist: pytest-cov<=6.0.0,>=5.0.0; extra == "complete"
Requires-Dist: pandas; extra == "complete"
Dynamic: license-file
